greydot_sdk/__init__.py
greydot_sdk-1.0.dist-info/METADATA
greydot_sdk-1.0.dist-info/WHEEL
greydot_sdk-1.0.dist-info/entry_points.txt
greydot_sdk-1.0.dist-info/top_level.txt
greydot_sdk-1.0.dist-info/RECORD
